[{
  "_id": {
    "$oid": "643174c34973c2ce8e3dc2e2"
  },
  "options": {},
  "indexes": [
    {
      "v": 2,
      "key": {
        "_id": 1
      },
      "name": "_id_",
      "ns": "Midjourney.accounts"
    }
  ],
  "uuid": "6d481303a057470ead5edbb1554e2274"
},{
  "_id": {
    "$oid": "645f4f9a19b2f7df7dcebb9d"
  },
  "user_id": "2114225793",
  "chat_id": 2114225793,
  "token": "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 ",
  "date": {
    "$date": {
      "$numberLong": "1683978698664"
    }
  },
  "used": false,
  "type": "gpt",
  "queue_count": 1
},{
  "_id": {
    "$oid": "645f4f9a19b2f7df7dcebb9e"
  },
  "user_id": "2114225793",
  "chat_id": 2114225793,
  "token": "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 ",
  "date": {
    "$date": {
      "$numberLong": "1683978698664"
    }
  },
  "used": false,
  "type": "gpt",
  "queue_count": 0
},{
  "_id": {
    "$oid": "645f4f9a19b2f7df7dcebb9f"
  },
  "user_id": "2114225793",
  "chat_id": 2114225793,
  "token": "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 ",
  "date": {
    "$date": {
      "$numberLong": "1683978698664"
    }
  },
  "used": false,
  "type": "gpt",
  "queue_count": 0
},{
  "_id": {
    "$oid": "647e5e17607583bdad84a23d"
  },
  "user_id": "2114225793",
  "chat_id": 2114225793,
  "token": "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",
  "date": {
    "$date": {
      "$numberLong": "1686014023236"
    }
  },
  "used": false,
  "type": "gpt",
  "queue_count": 0
},{
  "_id": {
    "$oid": "647e5e17607583bdad84a23e"
  },
  "user_id": "2114225793",
  "chat_id": 2114225793,
  "token": "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",
  "date": {
    "$date": {
      "$numberLong": "1686014023236"
    }
  },
  "used": false,
  "type": "gpt",
  "queue_count": 0
},{
  "_id": {
    "$oid": "647e5e17607583bdad84a23f"
  },
  "user_id": "2114225793",
  "chat_id": 2114225793,
  "token": "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",
  "date": {
    "$date": {
      "$numberLong": "1686014023236"
    }
  },
  "used": false,
  "type": "gpt",
  "queue_count": 0
},{
  "_id": {
    "$oid": "647e5e17607583bdad84a240"
  },
  "user_id": "2114225793",
  "chat_id": 2114225793,
  "token": "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",
  "date": {
    "$date": {
      "$numberLong": "1686014023236"
    }
  },
  "used": false,
  "type": "gpt",
  "queue_count": 0
},{
  "_id": {
    "$oid": "647e5e17607583bdad84a241"
  },
  "user_id": "2114225793",
  "chat_id": 2114225793,
  "token": "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",
  "date": {
    "$date": {
      "$numberLong": "1686014023236"
    }
  },
  "used": false,
  "type": "gpt",
  "queue_count": 0
},{
  "_id": {
    "$oid": "647e5e17607583bdad84a242"
  },
  "user_id": "2114225793",
  "chat_id": 2114225793,
  "token": "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",
  "date": {
    "$date": {
      "$numberLong": "1686014023236"
    }
  },
  "used": false,
  "type": "gpt",
  "queue_count": 0
},{
  "_id": {
    "$oid": "647e5e17607583bdad84a243"
  },
  "user_id": "2114225793",
  "chat_id": 2114225793,
  "token": "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",
  "date": {
    "$date": {
      "$numberLong": "1686014023236"
    }
  },
  "used": false,
  "type": "gpt",
  "queue_count": 0
},{
  "_id": {
    "$oid": "647e5e17607583bdad84a244"
  },
  "user_id": "2114225793",
  "chat_id": 2114225793,
  "token": "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",
  "date": {
    "$date": {
      "$numberLong": "1686014023236"
    }
  },
  "used": false,
  "type": "gpt",
  "queue_count": 0
},{
  "_id": {
    "$oid": "647e5e17607583bdad84a245"
  },
  "user_id": "2114225793",
  "chat_id": 2114225793,
  "token": "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",
  "date": {
    "$date": {
      "$numberLong": "1686014023236"
    }
  },
  "used": false,
  "type": "gpt",
  "queue_count": 0
},{
  "_id": {
    "$oid": "647e5e17607583bdad84a246"
  },
  "user_id": "2114225793",
  "chat_id": 2114225793,
  "token": "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",
  "date": {
    "$date": {
      "$numberLong": "1686014023236"
    }
  },
  "used": false,
  "type": "gpt",
  "queue_count": 0
},{
  "_id": {
    "$oid": "647e5e17607583bdad84a247"
  },
  "user_id": "2114225793",
  "chat_id": 2114225793,
  "token": "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",
  "date": {
    "$date": {
      "$numberLong": "1686014023236"
    }
  },
  "used": false,
  "type": "gpt",
  "queue_count": 0
},{
  "_id": {
    "$oid": "647e5e17607583bdad84a248"
  },
  "user_id": "2114225793",
  "chat_id": 2114225793,
  "token": "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",
  "date": {
    "$date": {
      "$numberLong": "1686014023236"
    }
  },
  "used": false,
  "type": "gpt",
  "queue_count": 0
},{
  "_id": {
    "$oid": "647e5e17607583bdad84a249"
  },
  "user_id": "2114225793",
  "chat_id": 2114225793,
  "token": "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",
  "date": {
    "$date": {
      "$numberLong": "1686014023236"
    }
  },
  "used": false,
  "type": "gpt",
  "queue_count": 0
},{
  "_id": {
    "$oid": "647e5e17607583bdad84a24a"
  },
  "user_id": "2114225793",
  "chat_id": 2114225793,
  "token": "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",
  "date": {
    "$date": {
      "$numberLong": "1686014023236"
    }
  },
  "used": false,
  "type": "gpt",
  "queue_count": 0
},{
  "_id": {
    "$oid": "647e5e17607583bdad84a24b"
  },
  "user_id": "2114225793",
  "chat_id": 2114225793,
  "token": "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",
  "date": {
    "$date": {
      "$numberLong": "1686014023236"
    }
  },
  "used": false,
  "type": "gpt",
  "queue_count": 0
},{
  "_id": {
    "$oid": "647e5e17607583bdad84a24c"
  },
  "user_id": "2114225793",
  "chat_id": 2114225793,
  "token": "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",
  "date": {
    "$date": {
      "$numberLong": "1686014023236"
    }
  },
  "used": false,
  "type": "gpt",
  "queue_count": 0
},{
  "_id": {
    "$oid": "647e5e17607583bdad84a24d"
  },
  "user_id": "2114225793",
  "chat_id": 2114225793,
  "token": "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",
  "date": {
    "$date": {
      "$numberLong": "1686014023236"
    }
  },
  "used": false,
  "type": "gpt",
  "queue_count": 0
},{
  "_id": {
    "$oid": "647e5e17607583bdad84a24e"
  },
  "user_id": "2114225793",
  "chat_id": 2114225793,
  "token": "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",
  "date": {
    "$date": {
      "$numberLong": "1686014023236"
    }
  },
  "used": false,
  "type": "gpt",
  "queue_count": 0
},{
  "_id": {
    "$oid": "647e5e17607583bdad84a24f"
  },
  "user_id": "2114225793",
  "chat_id": 2114225793,
  "token": "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",
  "date": {
    "$date": {
      "$numberLong": "1686014023236"
    }
  },
  "used": false,
  "type": "gpt",
  "queue_count": 0
},{
  "_id": {
    "$oid": "647e5e17607583bdad84a250"
  },
  "user_id": "2114225793",
  "chat_id": 2114225793,
  "token": "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",
  "date": {
    "$date": {
      "$numberLong": "1686014023236"
    }
  },
  "used": false,
  "type": "gpt",
  "queue_count": 0
},{
  "_id": {
    "$oid": "647e5e17607583bdad84a251"
  },
  "user_id": "2114225793",
  "chat_id": 2114225793,
  "token": "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",
  "date": {
    "$date": {
      "$numberLong": "1686014023236"
    }
  },
  "used": false,
  "type": "gpt",
  "queue_count": 0
},{
  "_id": {
    "$oid": "647e5e17607583bdad84a252"
  },
  "user_id": "2114225793",
  "chat_id": 2114225793,
  "token": "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",
  "date": {
    "$date": {
      "$numberLong": "1686014023236"
    }
  },
  "used": false,
  "type": "gpt",
  "queue_count": 0
},{
  "_id": {
    "$oid": "647e5e17607583bdad84a253"
  },
  "user_id": "2114225793",
  "chat_id": 2114225793,
  "token": "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",
  "date": {
    "$date": {
      "$numberLong": "1686014023236"
    }
  },
  "used": false,
  "type": "gpt",
  "queue_count": 0
},{
  "_id": {
    "$oid": "647e5e17607583bdad84a254"
  },
  "user_id": "2114225793",
  "chat_id": 2114225793,
  "token": "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",
  "date": {
    "$date": {
      "$numberLong": "1686014023236"
    }
  },
  "used": false,
  "type": "gpt",
  "queue_count": 0
},{
  "_id": {
    "$oid": "647e5e17607583bdad84a255"
  },
  "user_id": "2114225793",
  "chat_id": 2114225793,
  "token": "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",
  "date": {
    "$date": {
      "$numberLong": "1686014023236"
    }
  },
  "used": false,
  "type": "gpt",
  "queue_count": 0
},{
  "_id": {
    "$oid": "647e5e17607583bdad84a256"
  },
  "user_id": "2114225793",
  "chat_id": 2114225793,
  "token": "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",
  "date": {
    "$date": {
      "$numberLong": "1686014023236"
    }
  },
  "used": false,
  "type": "gpt",
  "queue_count": 0
},{
  "_id": {
    "$oid": "647e5e17607583bdad84a257"
  },
  "user_id": "2114225793",
  "chat_id": 2114225793,
  "token": "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",
  "date": {
    "$date": {
      "$numberLong": "1686014023236"
    }
  },
  "used": false,
  "type": "gpt",
  "queue_count": 0
},{
  "_id": {
    "$oid": "647e5e17607583bdad84a258"
  },
  "user_id": "2114225793",
  "chat_id": 2114225793,
  "token": "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",
  "date": {
    "$date": {
      "$numberLong": "1686014023236"
    }
  },
  "used": false,
  "type": "gpt",
  "queue_count": 0
},{
  "_id": {
    "$oid": "647e5e17607583bdad84a259"
  },
  "user_id": "2114225793",
  "chat_id": 2114225793,
  "token": "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",
  "date": {
    "$date": {
      "$numberLong": "1686014023236"
    }
  },
  "used": false,
  "type": "gpt",
  "queue_count": 0
},{
  "_id": {
    "$oid": "647e5e17607583bdad84a25a"
  },
  "user_id": "2114225793",
  "chat_id": 2114225793,
  "token": "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",
  "date": {
    "$date": {
      "$numberLong": "1686014023236"
    }
  },
  "used": false,
  "type": "gpt",
  "queue_count": 0
},{
  "_id": {
    "$oid": "647e5e17607583bdad84a25b"
  },
  "user_id": "2114225793",
  "chat_id": 2114225793,
  "token": "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",
  "date": {
    "$date": {
      "$numberLong": "1686014023236"
    }
  },
  "used": false,
  "type": "gpt",
  "queue_count": 0
},{
  "_id": {
    "$oid": "647e5e17607583bdad84a25c"
  },
  "user_id": "2114225793",
  "chat_id": 2114225793,
  "token": "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",
  "date": {
    "$date": {
      "$numberLong": "1686014023236"
    }
  },
  "used": false,
  "type": "gpt",
  "queue_count": 0
},{
  "_id": {
    "$oid": "647e5e17607583bdad84a25d"
  },
  "user_id": "2114225793",
  "chat_id": 2114225793,
  "token": "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",
  "date": {
    "$date": {
      "$numberLong": "1686014023236"
    }
  },
  "used": false,
  "type": "gpt",
  "queue_count": 0
},{
  "_id": {
    "$oid": "647e5e17607583bdad84a25e"
  },
  "user_id": "2114225793",
  "chat_id": 2114225793,
  "token": "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",
  "date": {
    "$date": {
      "$numberLong": "1686014023236"
    }
  },
  "used": false,
  "type": "gpt",
  "queue_count": 0
},{
  "_id": {
    "$oid": "647e5e17607583bdad84a25f"
  },
  "user_id": "2114225793",
  "chat_id": 2114225793,
  "token": "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",
  "date": {
    "$date": {
      "$numberLong": "1686014023236"
    }
  },
  "used": false,
  "type": "gpt",
  "queue_count": 0
},{
  "_id": {
    "$oid": "647e5e17607583bdad84a260"
  },
  "user_id": "2114225793",
  "chat_id": 2114225793,
  "token": "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",
  "date": {
    "$date": {
      "$numberLong": "1686014023236"
    }
  },
  "used": false,
  "type": "gpt",
  "queue_count": 0
},{
  "_id": {
    "$oid": "647e5e17607583bdad84a261"
  },
  "user_id": "2114225793",
  "chat_id": 2114225793,
  "token": "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",
  "date": {
    "$date": {
      "$numberLong": "1686014023236"
    }
  },
  "used": false,
  "type": "gpt",
  "queue_count": 0
},{
  "_id": {
    "$oid": "647e5e17607583bdad84a262"
  },
  "user_id": "2114225793",
  "chat_id": 2114225793,
  "token": "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",
  "date": {
    "$date": {
      "$numberLong": "1686014023236"
    }
  },
  "used": false,
  "type": "gpt",
  "queue_count": 0
},{
  "_id": {
    "$oid": "647e5e17607583bdad84a263"
  },
  "user_id": "2114225793",
  "chat_id": 2114225793,
  "token": "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",
  "date": {
    "$date": {
      "$numberLong": "1686014023236"
    }
  },
  "used": false,
  "type": "gpt",
  "queue_count": 0
},{
  "_id": {
    "$oid": "647e5dfe0ca6501e353c6b0a"
  },
  "user_id": "2114225793",
  "chat_id": 2114225793,
  "token": "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",
  "date": {
    "$date": {
      "$numberLong": "1686013998254"
    }
  },
  "used": false,
  "type": "gpt",
  "queue_count": 1
},{
  "_id": {
    "$oid": "647e5dfe0ca6501e353c6b0b"
  },
  "user_id": "2114225793",
  "chat_id": 2114225793,
  "token": "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",
  "date": {
    "$date": {
      "$numberLong": "1686013998254"
    }
  },
  "used": false,
  "type": "gpt",
  "queue_count": 0
},{
  "_id": {
    "$oid": "647e5dfe0ca6501e353c6b0c"
  },
  "user_id": "2114225793",
  "chat_id": 2114225793,
  "token": "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",
  "date": {
    "$date": {
      "$numberLong": "1686013998254"
    }
  },
  "used": false,
  "type": "gpt",
  "queue_count": 0
},{
  "_id": {
    "$oid": "647e5dfe0ca6501e353c6b0d"
  },
  "user_id": "2114225793",
  "chat_id": 2114225793,
  "token": "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",
  "date": {
    "$date": {
      "$numberLong": "1686013998254"
    }
  },
  "used": false,
  "type": "gpt",
  "queue_count": 0
},{
  "_id": {
    "$oid": "647e5dfe0ca6501e353c6b0e"
  },
  "user_id": "2114225793",
  "chat_id": 2114225793,
  "token": "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",
  "date": {
    "$date": {
      "$numberLong": "1686013998254"
    }
  },
  "used": false,
  "type": "gpt",
  "queue_count": 0
},{
  "_id": {
    "$oid": "647e5dfe0ca6501e353c6b0f"
  },
  "user_id": "2114225793",
  "chat_id": 2114225793,
  "token": "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",
  "date": {
    "$date": {
      "$numberLong": "1686013998254"
    }
  },
  "used": false,
  "type": "gpt",
  "queue_count": 0
},{
  "_id": {
    "$oid": "647e5dfe0ca6501e353c6b10"
  },
  "user_id": "2114225793",
  "chat_id": 2114225793,
  "token": "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",
  "date": {
    "$date": {
      "$numberLong": "1686013998254"
    }
  },
  "used": false,
  "type": "gpt",
  "queue_count": 0
},{
  "_id": {
    "$oid": "647e5dfe0ca6501e353c6b11"
  },
  "user_id": "2114225793",
  "chat_id": 2114225793,
  "token": "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",
  "date": {
    "$date": {
      "$numberLong": "1686013998254"
    }
  },
  "used": false,
  "type": "gpt",
  "queue_count": 0
},{
  "_id": {
    "$oid": "647e5dfe0ca6501e353c6b12"
  },
  "user_id": "2114225793",
  "chat_id": 2114225793,
  "token": "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",
  "date": {
    "$date": {
      "$numberLong": "1686013998254"
    }
  },
  "used": false,
  "type": "gpt",
  "queue_count": 0
},{
  "_id": {
    "$oid": "647e5dfe0ca6501e353c6b13"
  },
  "user_id": "2114225793",
  "chat_id": 2114225793,
  "token": "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",
  "date": {
    "$date": {
      "$numberLong": "1686013998254"
    }
  },
  "used": false,
  "type": "gpt",
  "queue_count": 0
},{
  "_id": {
    "$oid": "647e5dfe0ca6501e353c6b14"
  },
  "user_id": "2114225793",
  "chat_id": 2114225793,
  "token": "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",
  "date": {
    "$date": {
      "$numberLong": "1686013998254"
    }
  },
  "used": false,
  "type": "gpt",
  "queue_count": 0
},{
  "_id": {
    "$oid": "647e5dfe0ca6501e353c6b15"
  },
  "user_id": "2114225793",
  "chat_id": 2114225793,
  "token": "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",
  "date": {
    "$date": {
      "$numberLong": "1686013998254"
    }
  },
  "used": false,
  "type": "gpt",
  "queue_count": 0
},{
  "_id": {
    "$oid": "647e5dfe0ca6501e353c6b16"
  },
  "user_id": "2114225793",
  "chat_id": 2114225793,
  "token": "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",
  "date": {
    "$date": {
      "$numberLong": "1686013998254"
    }
  },
  "used": false,
  "type": "gpt",
  "queue_count": 0
},{
  "_id": {
    "$oid": "647e5dfe0ca6501e353c6b17"
  },
  "user_id": "2114225793",
  "chat_id": 2114225793,
  "token": "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",
  "date": {
    "$date": {
      "$numberLong": "1686013998254"
    }
  },
  "used": false,
  "type": "gpt",
  "queue_count": 0
},{
  "_id": {
    "$oid": "647e5dfe0ca6501e353c6b18"
  },
  "user_id": "2114225793",
  "chat_id": 2114225793,
  "token": "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",
  "date": {
    "$date": {
      "$numberLong": "1686013998254"
    }
  },
  "used": false,
  "type": "gpt",
  "queue_count": 0
},{
  "_id": {
    "$oid": "647e5dfe0ca6501e353c6b19"
  },
  "user_id": "2114225793",
  "chat_id": 2114225793,
  "token": "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",
  "date": {
    "$date": {
      "$numberLong": "1686013998254"
    }
  },
  "used": false,
  "type": "gpt",
  "queue_count": 0
},{
  "_id": {
    "$oid": "647e5dfe0ca6501e353c6b1a"
  },
  "user_id": "2114225793",
  "chat_id": 2114225793,
  "token": "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",
  "date": {
    "$date": {
      "$numberLong": "1686013998254"
    }
  },
  "used": false,
  "type": "gpt",
  "queue_count": 0
},{
  "_id": {
    "$oid": "647e5dfe0ca6501e353c6b1b"
  },
  "user_id": "2114225793",
  "chat_id": 2114225793,
  "token": "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",
  "date": {
    "$date": {
      "$numberLong": "1686013998254"
    }
  },
  "used": false,
  "type": "gpt",
  "queue_count": 0
},{
  "_id": {
    "$oid": "647e5dfe0ca6501e353c6b1c"
  },
  "user_id": "2114225793",
  "chat_id": 2114225793,
  "token": "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",
  "date": {
    "$date": {
      "$numberLong": "1686013998254"
    }
  },
  "used": false,
  "type": "gpt",
  "queue_count": 0
},{
  "_id": {
    "$oid": "647e5dfe0ca6501e353c6b1d"
  },
  "user_id": "2114225793",
  "chat_id": 2114225793,
  "token": "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",
  "date": {
    "$date": {
      "$numberLong": "1686013998254"
    }
  },
  "used": false,
  "type": "gpt",
  "queue_count": 0
},{
  "_id": {
    "$oid": "647e5dfe0ca6501e353c6b1e"
  },
  "user_id": "2114225793",
  "chat_id": 2114225793,
  "token": "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",
  "date": {
    "$date": {
      "$numberLong": "1686013998254"
    }
  },
  "used": false,
  "type": "gpt",
  "queue_count": 0
},{
  "_id": {
    "$oid": "647e5dfe0ca6501e353c6b1f"
  },
  "user_id": "2114225793",
  "chat_id": 2114225793,
  "token": "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",
  "date": {
    "$date": {
      "$numberLong": "1686013998254"
    }
  },
  "used": false,
  "type": "gpt",
  "queue_count": 0
},{
  "_id": {
    "$oid": "647e5dfe0ca6501e353c6b20"
  },
  "user_id": "2114225793",
  "chat_id": 2114225793,
  "token": "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",
  "date": {
    "$date": {
      "$numberLong": "1686013998254"
    }
  },
  "used": false,
  "type": "gpt",
  "queue_count": 0
},{
  "_id": {
    "$oid": "647e5dfe0ca6501e353c6b21"
  },
  "user_id": "2114225793",
  "chat_id": 2114225793,
  "token": "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",
  "date": {
    "$date": {
      "$numberLong": "1686013998254"
    }
  },
  "used": false,
  "type": "gpt",
  "queue_count": 0
},{
  "_id": {
    "$oid": "647e5dfe0ca6501e353c6b22"
  },
  "user_id": "2114225793",
  "chat_id": 2114225793,
  "token": "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",
  "date": {
    "$date": {
      "$numberLong": "1686013998254"
    }
  },
  "used": false,
  "type": "gpt",
  "queue_count": 0
},{
  "_id": {
    "$oid": "647e5dfe0ca6501e353c6b23"
  },
  "user_id": "2114225793",
  "chat_id": 2114225793,
  "token": "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",
  "date": {
    "$date": {
      "$numberLong": "1686013998254"
    }
  },
  "used": false,
  "type": "gpt",
  "queue_count": 0
},{
  "_id": {
    "$oid": "647e5dfe0ca6501e353c6b24"
  },
  "user_id": "2114225793",
  "chat_id": 2114225793,
  "token": "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",
  "date": {
    "$date": {
      "$numberLong": "1686013998254"
    }
  },
  "used": false,
  "type": "gpt",
  "queue_count": 0
},{
  "_id": {
    "$oid": "647e5dfe0ca6501e353c6b25"
  },
  "user_id": "2114225793",
  "chat_id": 2114225793,
  "token": "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",
  "date": {
    "$date": {
      "$numberLong": "1686013998254"
    }
  },
  "used": false,
  "type": "gpt",
  "queue_count": 0
},{
  "_id": {
    "$oid": "647e5dfe0ca6501e353c6b26"
  },
  "user_id": "2114225793",
  "chat_id": 2114225793,
  "token": "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",
  "date": {
    "$date": {
      "$numberLong": "1686013998254"
    }
  },
  "used": false,
  "type": "gpt",
  "queue_count": 0
},{
  "_id": {
    "$oid": "647e5dfe0ca6501e353c6b27"
  },
  "user_id": "2114225793",
  "chat_id": 2114225793,
  "token": "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",
  "date": {
    "$date": {
      "$numberLong": "1686013998254"
    }
  },
  "used": false,
  "type": "gpt",
  "queue_count": 0
},{
  "_id": {
    "$oid": "647e5dfe0ca6501e353c6b28"
  },
  "user_id": "2114225793",
  "chat_id": 2114225793,
  "token": "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",
  "date": {
    "$date": {
      "$numberLong": "1686013998254"
    }
  },
  "used": false,
  "type": "gpt",
  "queue_count": 0
},{
  "_id": {
    "$oid": "647e5dfe0ca6501e353c6b29"
  },
  "user_id": "2114225793",
  "chat_id": 2114225793,
  "token": "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",
  "date": {
    "$date": {
      "$numberLong": "1686013998254"
    }
  },
  "used": false,
  "type": "gpt",
  "queue_count": 0
},{
  "_id": {
    "$oid": "647e5dfe0ca6501e353c6b2a"
  },
  "user_id": "2114225793",
  "chat_id": 2114225793,
  "token": "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",
  "date": {
    "$date": {
      "$numberLong": "1686013998254"
    }
  },
  "used": false,
  "type": "gpt",
  "queue_count": 0
},{
  "_id": {
    "$oid": "647e5dfe0ca6501e353c6b2b"
  },
  "user_id": "2114225793",
  "chat_id": 2114225793,
  "token": "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",
  "date": {
    "$date": {
      "$numberLong": "1686013998254"
    }
  },
  "used": false,
  "type": "gpt",
  "queue_count": 0
},{
  "_id": {
    "$oid": "647e5dfe0ca6501e353c6b2c"
  },
  "user_id": "2114225793",
  "chat_id": 2114225793,
  "token": "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",
  "date": {
    "$date": {
      "$numberLong": "1686013998254"
    }
  },
  "used": false,
  "type": "gpt",
  "queue_count": 0
},{
  "_id": {
    "$oid": "647e5dfe0ca6501e353c6b2d"
  },
  "user_id": "2114225793",
  "chat_id": 2114225793,
  "token": "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",
  "date": {
    "$date": {
      "$numberLong": "1686013998254"
    }
  },
  "used": false,
  "type": "gpt",
  "queue_count": 0
},{
  "_id": {
    "$oid": "647e5dfe0ca6501e353c6b2e"
  },
  "user_id": "2114225793",
  "chat_id": 2114225793,
  "token": "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",
  "date": {
    "$date": {
      "$numberLong": "1686013998254"
    }
  },
  "used": false,
  "type": "gpt",
  "queue_count": 0
},{
  "_id": {
    "$oid": "647e5dfe0ca6501e353c6b2f"
  },
  "user_id": "2114225793",
  "chat_id": 2114225793,
  "token": "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",
  "date": {
    "$date": {
      "$numberLong": "1686013998254"
    }
  },
  "used": false,
  "type": "gpt",
  "queue_count": 0
},{
  "_id": {
    "$oid": "647e5dfe0ca6501e353c6b30"
  },
  "user_id": "2114225793",
  "chat_id": 2114225793,
  "token": "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",
  "date": {
    "$date": {
      "$numberLong": "1686013998255"
    }
  },
  "used": false,
  "type": "gpt",
  "queue_count": 0
},{
  "_id": {
    "$oid": "647e5dfe0ca6501e353c6b31"
  },
  "user_id": "2114225793",
  "chat_id": 2114225793,
  "token": "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",
  "date": {
    "$date": {
      "$numberLong": "1686013998255"
    }
  },
  "used": false,
  "type": "gpt",
  "queue_count": 0
},{
  "_id": {
    "$oid": "647e5dfe0ca6501e353c6b32"
  },
  "user_id": "2114225793",
  "chat_id": 2114225793,
  "token": "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",
  "date": {
    "$date": {
      "$numberLong": "1686013998255"
    }
  },
  "used": false,
  "type": "gpt",
  "queue_count": 0
},{
  "_id": {
    "$oid": "647e5dfe0ca6501e353c6b33"
  },
  "user_id": "2114225793",
  "chat_id": 2114225793,
  "token": "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",
  "date": {
    "$date": {
      "$numberLong": "1686013998255"
    }
  },
  "used": false,
  "type": "gpt",
  "queue_count": 0
},{
  "_id": {
    "$oid": "647e5dfe0ca6501e353c6b34"
  },
  "user_id": "2114225793",
  "chat_id": 2114225793,
  "token": "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",
  "date": {
    "$date": {
      "$numberLong": "1686013998255"
    }
  },
  "used": false,
  "type": "gpt",
  "queue_count": 0
},{
  "_id": {
    "$oid": "647e5dfe0ca6501e353c6b35"
  },
  "user_id": "2114225793",
  "chat_id": 2114225793,
  "token": "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",
  "date": {
    "$date": {
      "$numberLong": "1686013998255"
    }
  },
  "used": false,
  "type": "gpt",
  "queue_count": 0
},{
  "_id": {
    "$oid": "647e5dfe0ca6501e353c6b36"
  },
  "user_id": "2114225793",
  "chat_id": 2114225793,
  "token": "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",
  "date": {
    "$date": {
      "$numberLong": "1686013998255"
    }
  },
  "used": false,
  "type": "gpt",
  "queue_count": 0
},{
  "_id": {
    "$oid": "647e5dfe0ca6501e353c6b37"
  },
  "user_id": "2114225793",
  "chat_id": 2114225793,
  "token": "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",
  "date": {
    "$date": {
      "$numberLong": "1686013998255"
    }
  },
  "used": false,
  "type": "gpt",
  "queue_count": 0
},{
  "_id": {
    "$oid": "647e5dfe0ca6501e353c6b38"
  },
  "user_id": "2114225793",
  "chat_id": 2114225793,
  "token": "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",
  "date": {
    "$date": {
      "$numberLong": "1686013998255"
    }
  },
  "used": false,
  "type": "gpt",
  "queue_count": 0
},{
  "_id": {
    "$oid": "647e5dfe0ca6501e353c6b39"
  },
  "user_id": "2114225793",
  "chat_id": 2114225793,
  "token": "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",
  "date": {
    "$date": {
      "$numberLong": "1686013998255"
    }
  },
  "used": false,
  "type": "gpt",
  "queue_count": 0
},{
  "_id": {
    "$oid": "647e5dfe0ca6501e353c6b3a"
  },
  "user_id": "2114225793",
  "chat_id": 2114225793,
  "token": "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",
  "date": {
    "$date": {
      "$numberLong": "1686013998255"
    }
  },
  "used": false,
  "type": "gpt",
  "queue_count": 0
},{
  "_id": {
    "$oid": "647e5dfe0ca6501e353c6b3b"
  },
  "user_id": "2114225793",
  "chat_id": 2114225793,
  "token": "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",
  "date": {
    "$date": {
      "$numberLong": "1686013998255"
    }
  },
  "used": false,
  "type": "gpt",
  "queue_count": 0
},{
  "_id": {
    "$oid": "647e5dfe0ca6501e353c6b3c"
  },
  "user_id": "2114225793",
  "chat_id": 2114225793,
  "token": "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",
  "date": {
    "$date": {
      "$numberLong": "1686013998255"
    }
  },
  "used": false,
  "type": "gpt",
  "queue_count": 0
},{
  "_id": {
    "$oid": "647e5dfe0ca6501e353c6b3d"
  },
  "user_id": "2114225793",
  "chat_id": 2114225793,
  "token": "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",
  "date": {
    "$date": {
      "$numberLong": "1686013998255"
    }
  },
  "used": false,
  "type": "gpt",
  "queue_count": 0
},{
  "_id": {
    "$oid": "647e5dfe0ca6501e353c6b3e"
  },
  "user_id": "2114225793",
  "chat_id": 2114225793,
  "token": "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",
  "date": {
    "$date": {
      "$numberLong": "1686013998255"
    }
  },
  "used": false,
  "type": "gpt",
  "queue_count": 0
},{
  "_id": {
    "$oid": "647e5dfe0ca6501e353c6b3f"
  },
  "user_id": "2114225793",
  "chat_id": 2114225793,
  "token": "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",
  "date": {
    "$date": {
      "$numberLong": "1686013998255"
    }
  },
  "used": false,
  "type": "gpt",
  "queue_count": 0
},{
  "_id": {
    "$oid": "647e5dfe0ca6501e353c6b40"
  },
  "user_id": "2114225793",
  "chat_id": 2114225793,
  "token": "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",
  "date": {
    "$date": {
      "$numberLong": "1686013998255"
    }
  },
  "used": false,
  "type": "gpt",
  "queue_count": 0
},{
  "_id": {
    "$oid": "647e5dfe0ca6501e353c6b41"
  },
  "user_id": "2114225793",
  "chat_id": 2114225793,
  "token": "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",
  "date": {
    "$date": {
      "$numberLong": "1686013998255"
    }
  },
  "used": false,
  "type": "gpt",
  "queue_count": 0
},{
  "_id": {
    "$oid": "647e5dfe0ca6501e353c6b42"
  },
  "user_id": "2114225793",
  "chat_id": 2114225793,
  "token": "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",
  "date": {
    "$date": {
      "$numberLong": "1686013998255"
    }
  },
  "used": false,
  "type": "gpt",
  "queue_count": 0
},{
  "_id": {
    "$oid": "647e5dfe0ca6501e353c6b43"
  },
  "user_id": "2114225793",
  "chat_id": 2114225793,
  "token": "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",
  "date": {
    "$date": {
      "$numberLong": "1686013998255"
    }
  },
  "used": false,
  "type": "gpt",
  "queue_count": 0
},{
  "_id": {
    "$oid": "647e5dfe0ca6501e353c6b44"
  },
  "user_id": "2114225793",
  "chat_id": 2114225793,
  "token": "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",
  "date": {
    "$date": {
      "$numberLong": "1686013998255"
    }
  },
  "used": false,
  "type": "gpt",
  "queue_count": 0
},{
  "_id": {
    "$oid": "647e5dfe0ca6501e353c6b45"
  },
  "user_id": "2114225793",
  "chat_id": 2114225793,
  "token": "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",
  "date": {
    "$date": {
      "$numberLong": "1686013998255"
    }
  },
  "used": false,
  "type": "gpt",
  "queue_count": 0
},{
  "_id": {
    "$oid": "647e5dfe0ca6501e353c6b46"
  },
  "user_id": "2114225793",
  "chat_id": 2114225793,
  "token": "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",
  "date": {
    "$date": {
      "$numberLong": "1686013998255"
    }
  },
  "used": false,
  "type": "gpt",
  "queue_count": 0
},{
  "_id": {
    "$oid": "647e5dfe0ca6501e353c6b47"
  },
  "user_id": "2114225793",
  "chat_id": 2114225793,
  "token": "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",
  "date": {
    "$date": {
      "$numberLong": "1686013998255"
    }
  },
  "used": false,
  "type": "gpt",
  "queue_count": 0
},{
  "_id": {
    "$oid": "647e5dfe0ca6501e353c6b48"
  },
  "user_id": "2114225793",
  "chat_id": 2114225793,
  "token": "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",
  "date": {
    "$date": {
      "$numberLong": "1686013998255"
    }
  },
  "used": false,
  "type": "gpt",
  "queue_count": 0
},{
  "_id": {
    "$oid": "647e5dfe0ca6501e353c6b49"
  },
  "user_id": "2114225793",
  "chat_id": 2114225793,
  "token": "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",
  "date": {
    "$date": {
      "$numberLong": "1686013998255"
    }
  },
  "used": false,
  "type": "gpt",
  "queue_count": 0
},{
  "_id": {
    "$oid": "647e5dfe0ca6501e353c6b4a"
  },
  "user_id": "2114225793",
  "chat_id": 2114225793,
  "token": "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",
  "date": {
    "$date": {
      "$numberLong": "1686013998255"
    }
  },
  "used": false,
  "type": "gpt",
  "queue_count": 0
}]